brainvoyagertools/__init__.py
brainvoyagertools/ctr.py
brainvoyagertools/mdm.py
brainvoyagertools/prt.py
brainvoyagertools/sdm.py
brainvoyagertools/voi.py
brainvoyagertools-0.4.0.dist-info/LICENSE
brainvoyagertools-0.4.0.dist-info/METADATA
brainvoyagertools-0.4.0.dist-info/WHEEL
brainvoyagertools-0.4.0.dist-info/top_level.txt
brainvoyagertools-0.4.0.dist-info/RECORD
