Metadata-Version: 2.1
Name: brainvoyagertools
Version: 0.4.0
Summary: BrainVoyager Tools - An object-oriented approach to create, read and write common plain-text BrainVoyager input formats with Python
Home-page: https://github.com/fladd/brainvoyagertools
Author: Florian Krause
Author-email: me@floriankrause.org
Classifier: Programming Language :: Python :: 3
Classifier: License :: OSI Approved :: GNU General Public License v3 (GPLv3)
Classifier: Operating System :: OS Independent
Requires-Python: >=3.6
License-File: LICENSE
Requires-Dist: numpy (<2,>=1)
Requires-Dist: scipy (<2,>=1)
